shiny_coloris/__init__.py
shiny_coloris/color_picker.py
shiny_coloris/py.typed
shiny_coloris/assets/coloris.min.css
shiny_coloris/assets/coloris.min.js
shiny_coloris-0.1.0.dist-info/METADATA
shiny_coloris-0.1.0.dist-info/WHEEL
shiny_coloris-0.1.0.dist-info/licenses/LICENSE
shiny_coloris-0.1.0.dist-info/RECORD
