Metadata-Version: 2.4
Name: shiny-coloris
Version: 0.1.0
Summary: Wrapper around js lib Coloris for use in Shiny.
Project-URL: Homepage, https://github.com/nuayge/shiny-coloris
Project-URL: Issues, https://github.com/nuayge/shiny-coloris/issues
Author-email: Val <va9602@gmail.com>
License: MIT License
License-File: LICENSE
Classifier: License :: OSI Approved :: MIT License
Classifier: Operating System :: OS Independent
Classifier: Programming Language :: Python :: 3
Requires-Python: >=3.11
Requires-Dist: htmltools>=0.6.0
Requires-Dist: shiny>=1.4.0
